newick.py
newick-1.9.0.dist-info/LICENSE
newick-1.9.0.dist-info/METADATA
newick-1.9.0.dist-info/WHEEL
newick-1.9.0.dist-info/top_level.txt
newick-1.9.0.dist-info/RECORD
